{
    "H031": [
        "VPTD"
    ],
    "H321": [
        "VPTD"
    ],
    "VTZ": [
        "VPTD",
        "BCL"
    ],
    "MOV": [
        "VPTD",
        "BCL"
    ],
    "BC": [
        "VPTD",
        "BCL",
        "CSKH",
        "CQCT",
        "Dashboard N\u0103m"
    ],
    "ANM": [
        "VPTD",
        "CQCT",
        "BCL"
    ],
    "VTS": [
        "VPTD",
        "BCL",
        "CSKH",
        "QTDL",
        "CNTT",
        "CQCT",
        "BAN_DO",
        "Dashboard N\u0103m"
    ],
    "T037": [
        "VPTD"
    ],
    "T054": [
        "VPTD"
    ],
    "H019": [
        "VPTD"
    ],
    "N351": [
        "VPTD"
    ],
    "H039": [
        "VPTD"
    ],
    "B240": [
        "VPTD"
    ],
    "VDTC": [
        "VPTD",
        "CQCT"
    ],
    "VTP": [
        "VPTD",
        "BCL"
    ],
    "XNK": [
        "VPTD",
        "CQCT",
        "BCL",
        "DT_TC"
    ],
    "XMCP": [
        "VPTD",
        "CQCT",
        "BCL"
    ],
    "IDC": [
        "VPTD",
        "CQCT",
        "BCL",
        "DT_TC"
    ],
    "A076": [
        "VPTD"
    ],
    "H711": [
        "VPTD"
    ],
    "D067": [
        "VPTD"
    ],
    "P057": [
        "VPTD"
    ],
    "G059": [
        "VPTD"
    ],
    "H320": [
        "VPTD"
    ],
    "D061": [
        "VPTD"
    ],
    "VBD": [
        "VPTD",
        "BCL"
    ],
    "VHK": [
        "VPTD",
        "BCL"
    ],
    "CTM": [
        "BCL",
        "QTDL",
        "VPTD"
    ],
    "NAT": [
        "BCL",
        "VPTD"
    ],
    "VDS": [
        "BCL",
        "VPTD",
        "CSKH",
        "CNTT",
        "QTDL",
        "CQCT",
        "BAN_DO",
        "Dashboard tu\u1ea7n ch\u1ec9 huy"
    ],
    "VTL": [
        "BCL",
        "VPTD"
    ],
    "CT": [
        "VPTD",
        "CQCT",
        "BCL"
    ],
    "TVTK": [
        "VPTD",
        "CQCT",
        "BCL"
    ],
    "TH": [
        "VPTD",
        "CNTT",
        "CQCT",
        "BCL"
    ],
    "M3": [
        "VPTD",
        "BCL"
    ],
    "M1": [
        "VPTD",
        "BCL"
    ],
    "VNC": [
        "VPTD",
        "BCL"
    ],
    "VTTNEWNEW": [
        "VPTD",
        "BCL",
        "CSKH",
        "CNTT",
        "QTDL",
        "VPTD_6T",
        "VPTD_6M",
        "CQCT",
        "BAN_DO",
        "Dashboard N\u0103m",
        "DB_CNCNC",
        "DB_TTKT",
        "DB_DTXD",
        "DB_DN",
        "DB_CQCT",
        "DT_TC",
        "DB_TCNL",
        "DB_CNTT"
    ],
    "VTC": [
        "VPTD",
        "BCL"
    ],
    "STL": [
        "VPTD",
        "BCL"
    ],
    "MYN": [
        "VPTD",
        "BCL"
    ],
    "VTG": [
        "VPTD",
        "BCL",
        "VPTD_6T",
        "VPTD_6M",
        "CQCT",
        "BAN_DO",
        "Dashboard N\u0103m"
    ],
    "KGM": [
        "VPTD",
        "QTDL",
        "CQCT",
        "BCL"
    ],
    "Q053": [
        "VPTD"
    ],
    "Q510": [
        "VPTD"
    ],
    "D511": [
        "VPTD"
    ],
    "VTE": [
        "VPTD"
    ],
    "TD": [
        "BCL",
        "VPTD",
        "CSKH",
        "DTTC",
        "CNTT",
        "QTDL",
        "VPTD_6T",
        "VPTD_6M",
        "CQCT",
        "BAN_DO",
        "Dashboard N\u0103m",
        "Dashboard tu\u1ea7n ch\u1ec9 huy",
        "B\u1ea3n \u0111\u1ed3 n\u0103m",
        "Dashboard KPI QTDL",
        "DB_TTKT",
        "DT_TC",
        "DB_DN",
        "DB_CQCT",
        "DB_TCKT",
        "DB_CNTT",
        "DB_DTXD",
        "DB_CNCNC",
        "DB_TCNL",
        "DB_THTT"
    ],
    "TN": [
        "BCL"
    ],
    "VTN": [
        "VPTD",
        "QTDL",
        "CNTT"
    ],
    "TTTT": [
        "VPTD"
    ],
    "B241": [
        "VPTD"
    ],
    "T008": [
        "VPTD",
        "VPTD_6M"
    ],
    "V064": [
        "VPTD"
    ],
    "V211": [
        "VPTD"
    ],
    "B650": [
        "VPTD"
    ],
    "T074": [
        "VPTD"
    ],
    "B781": [
        "VPTD"
    ],
    "T027": [
        "VPTD"
    ],
    "T280": [
        "VPTD"
    ],
    "T073": [
        "VPTD"
    ],
    "T036": [
        "VPTD"
    ],
    "S079": [
        "VPTD"
    ],
    "S022": [
        "VPTD"
    ],
    "C026": [
        "VPTD"
    ],
    "Q055": [
        "VPTD"
    ],
    "C710": [
        "VPTD"
    ],
    "Q033": [
        "VPTD"
    ],
    "D230": [
        "VPTD"
    ],
    "Q052": [
        "VPTD"
    ],
    "N068": [
        "VPTD"
    ],
    "N350": [
        "VPTD"
    ],
    "N030": [
        "VPTD"
    ],
    "L025": [
        "VPTD"
    ],
    "L063": [
        "VPTD"
    ],
    "H018": [
        "VPTD"
    ],
    "L072": [
        "VPTD"
    ],
    "K060": [
        "VPTD"
    ],
    "K077": [
        "VPTD"
    ],
    "Y029": [
        "VPTD"
    ],
    "V070": [
        "VPTD"
    ],
    "T066": [
        "VPTD"
    ],
    "B651": [
        "VPTD"
    ],
    "B075": [
        "VPTD"
    ],
    "C780": [
        "VPTD"
    ],
    "N038": [
        "VPTD"
    ],
    "K058": [
        "VPTD"
    ],
    "D500": [
        "VPTD"
    ],
    "B056": [
        "VPTD"
    ],
    "B281": [
        "VPTD"
    ],
    "SXTB": [
        "VPTD",
        "BCL"
    ],
    "NaN": [
        "QTDL",
        NaN
    ],
    "VTA": [
        "VPTD"
    ],
    "HVT": [
        "VPTD"
    ],
    "BDS": [
        "VPTD",
        "BCL"
    ],
    "D501": [
        "VPTD"
    ],
    "L020": [
        "VPTD"
    ],
    "H004": [
        "VPTD"
    ],
    "P210": [
        "VPTD"
    ],
    "TSS": [
        "VPTD"
    ],
    "B062": [
        "VPTD"
    ],
    "L231": [
        "VPTD"
    ],
    "VMC": [
        "VPTD"
    ],
    "CNTT": [
        "BCL"
    ],
    "KTM": [
        "BCL"
    ],
    "DVK": [
        "BCL"
    ],
    "KXL": [
        "BCL"
    ],
    "H004003": [
        "VPTD"
    ]
}